garth_mcp_server/__init__.py
mseep_garth_mcp_server-0.0.0.dist-info/licenses/LICENSE
mseep_garth_mcp_server-0.0.0.dist-info/METADATA
mseep_garth_mcp_server-0.0.0.dist-info/WHEEL
mseep_garth_mcp_server-0.0.0.dist-info/entry_points.txt
mseep_garth_mcp_server-0.0.0.dist-info/top_level.txt
mseep_garth_mcp_server-0.0.0.dist-info/RECORD
